tools/__init__.py
tools/file/__init__.py
tools/file/data_comparator.py
tools/file/extrat_pdf.py
tools/file/filemanager.py
tools/file/github.py
tools/gcp/__init__.py
tools/gcp/auth.py
tools/gcp/cloud_storage.py
tools/gcp/docker_image_manager.py
tools/gcp/firestoremanager.py
tools/gcp/storagemager.py
tools/web/__init__.py
tools/web/installer.py
tools/web/webdriver.py
xik_tools-0.89.dist-info/METADATA
xik_tools-0.89.dist-info/WHEEL
xik_tools-0.89.dist-info/entry_points.txt
xik_tools-0.89.dist-info/top_level.txt
xik_tools-0.89.dist-info/RECORD
