Metadata-Version: 2.4
Name: xik_tools
Version: 0.89
Summary: tools for web
Home-page: https://github.com/xikest/tools
Author: xikest
Project-URL: Source, https://github.com/xikest/tools
Project-URL: Bug Tracker, https://github.com/xikest/tools
Requires-Python: >=3.8
Requires-Dist: pandas
Requires-Dist: selenium
Requires-Dist: openpyxl
Dynamic: author
Dynamic: home-page
Dynamic: project-url
Dynamic: requires-dist
Dynamic: requires-python
Dynamic: summary
